firedm/FireDM.py
firedm/__init__.py
firedm/__main__.py
firedm/about.py
firedm/brain.py
firedm/cmdview.py
firedm/config.py
firedm/controller.py
firedm/downloaditem.py
firedm/iconsbase64.py
firedm/model.py
firedm/setting.py
firedm/systray.py
firedm/themes.py
firedm/tkview.py
firedm/update.py
firedm/utils.py
firedm/version.py
firedm/view.py
firedm/worker.py
FireDM-2022.4.14.dist-info/LICENSE
FireDM-2022.4.14.dist-info/METADATA
FireDM-2022.4.14.dist-info/WHEEL
FireDM-2022.4.14.dist-info/entry_points.txt
FireDM-2022.4.14.dist-info/top_level.txt
FireDM-2022.4.14.dist-info/RECORD
