Metadata-Version: 2.1
Name: FireDM
Version: 2022.4.14
Summary: download manager
Home-page: https://github.com/firedm/FireDM 
Author: Mahmoud Elshahat
Author-email: info.pyidm@gmail.com
License: UNKNOWN
Project-URL: Source, https://github.com/firedm/FireDM
Project-URL: Tracker, https://github.com/firedm/FireDM/issues
Project-URL: Releases, https://github.com/firedm/FireDM/releases
Project-URL: Screenshots, https://github.com/firedm/FireDM/issues/13#issuecomment-689337428
Keywords: internet download manager youtube hls pycurl curl youtube-dl tkinter
Platform: UNKNOWN
Classifier: Programming Language :: Python :: 3
Classifier: Programming Language :: Python :: 3.6
Classifier: Programming Language :: Python :: 3.7
Classifier: Programming Language :: Python :: 3.8
Classifier: License :: OSI Approved :: GNU Lesser General Public License v3 or later (LGPLv3+)
Classifier: Operating System :: OS Independent
Requires-Python: >=3.6
Requires-Dist: Pillow (>=6.0.0)
Requires-Dist: awesometkinter (>=2021.6.4)
Requires-Dist: certifi
Requires-Dist: packaging
Requires-Dist: plyer
Requires-Dist: pycurl
Requires-Dist: pystray
Requires-Dist: youtube-dl
Requires-Dist: yt-dlp
Requires-Dist: distro ; platform_system == "Linux"
